ChangeLog.md
INSTALL.md
LICENSE.md
MANIFEST.in
README.md
setup.py
doc/Makefile
doc/README.md
doc/index.html
doc/installation_index.html
doc/jsdoc-config.json
doc/tutorial_index.html
doc/bootstrap/css/bootstrap-theme.min.css
doc/bootstrap/css/bootstrap.min.css
doc/bootstrap/fonts/glyphicons-halflings-regular.eot
doc/bootstrap/fonts/glyphicons-halflings-regular.svg
doc/bootstrap/fonts/glyphicons-halflings-regular.ttf
doc/bootstrap/fonts/glyphicons-halflings-regular.woff
doc/bootstrap/fonts/glyphicons-halflings-regular.woff2
doc/bootstrap/js/bootstrap.min.js
doc/bootstrap/js/jquery-2.2.3.min.js
doc/files/files.zip
doc/img/emperor_heading.png
doc/img/favicon.ico
doc/img/sample_1.png
doc/source/conf.py
doc/source/description.rst
doc/source/examples.rst
doc/source/formats.rst
doc/source/index.rst
doc/source/js_integration.rst
doc/source/_static/copybutton.js
doc/source/_static/style.css
doc/source/_templates/layout.html
doc/source/_templates/autosummary/attribute.rst
doc/source/_templates/autosummary/class.rst
doc/source/_templates/autosummary/method.rst
doc/source/tutorials/animations.rst
doc/source/tutorials/trajectories.png
emperor/__init__.py
emperor/_format_strings.py
emperor/_pandas.py
emperor/core.py
emperor/format.py
emperor/util.py
emperor.egg-info/PKG-INFO
emperor.egg-info/SOURCES.txt
emperor.egg-info/dependency_links.txt
emperor.egg-info/requires.txt
emperor.egg-info/top_level.txt
emperor/qiime_backports/__init__.py
emperor/qiime_backports/make_3d_plots.py
emperor/qiime_backports/util.py
emperor/support_files/README.md
emperor/support_files/css/emperor.css
emperor/support_files/img/emperor.png
emperor/support_files/img/favicon.ico
emperor/support_files/img/pause.png
emperor/support_files/img/play.png
emperor/support_files/img/reset.png
emperor/support_files/js/abc-view-controller.js
emperor/support_files/js/animate.js
emperor/support_files/js/animations-controller.js
emperor/support_files/js/axes-controller.js
emperor/support_files/js/color-editor.js
emperor/support_files/js/color-view-controller.js
emperor/support_files/js/controller.js
emperor/support_files/js/draw.js
emperor/support_files/js/model.js
