Metadata-Version: 2.1
Name: emperor
Version: 1.0.5
Summary: Emperor
Home-page: http://github.com/biocore/emperor
Author: Antonio Gonzalez Pena, Meg Pirrung & Yoshiki Vazquez Baeza
Author-email: yoshiki89@gmail.com
Maintainer: Emperor development team
Maintainer-email: yoshiki89@gmail.com
License: BSD-3-Clause
Classifier: Development Status :: 5 - Production/Stable
Classifier: License :: OSI Approved :: BSD License
Classifier: Topic :: Software Development :: Libraries :: Application Frameworks
Classifier: Topic :: Software Development :: User Interfaces
Classifier: Programming Language :: Python
Classifier: Programming Language :: Python :: 3.6
Classifier: Programming Language :: Python :: 3.7
Classifier: Programming Language :: Python :: 3.8
Classifier: Programming Language :: Python :: Implementation :: CPython
Classifier: Operating System :: OS Independent
Classifier: Operating System :: POSIX
Classifier: Operating System :: MacOS :: MacOS X
License-File: LICENSE.md
Requires-Dist: numpy>=1.7
Requires-Dist: scipy>=0.17.0
Requires-Dist: click
Requires-Dist: pandas
Requires-Dist: scikit-bio>=0.4.1
Requires-Dist: jinja2>=2.9
Requires-Dist: future
Provides-Extra: doc
Requires-Dist: Sphinx<4; extra == "doc"
Requires-Dist: jinja2<3.1,>=2.9; extra == "doc"
Requires-Dist: sphinx-bootstrap-theme; extra == "doc"
Requires-Dist: numpydoc; extra == "doc"
Provides-Extra: test
Requires-Dist: pep8; extra == "test"
Requires-Dist: flake8; extra == "test"
Requires-Dist: nose; extra == "test"
Provides-Extra: all
Requires-Dist: numpy>=1.7; extra == "all"
Requires-Dist: scipy>=0.17.0; extra == "all"
Requires-Dist: click; extra == "all"
Requires-Dist: pandas; extra == "all"
Requires-Dist: scikit-bio>=0.4.1; extra == "all"
Requires-Dist: jinja2>=2.9; extra == "all"
Requires-Dist: future; extra == "all"
Requires-Dist: Sphinx<4; extra == "all"
Requires-Dist: jinja2<3.1,>=2.9; extra == "all"
Requires-Dist: sphinx-bootstrap-theme; extra == "all"
Requires-Dist: numpydoc; extra == "all"
Requires-Dist: pep8; extra == "all"
Requires-Dist: flake8; extra == "all"
Requires-Dist: nose; extra == "all"
